Metadata-Version: 2.1
Name: aspose-tex-net
Version: 25.8.0
Summary: Aspose.TeX for Python via .NET is a library that enables your Python applications to typeset TeX files and obtain output documents in file formats, such as XPS, PDF, JPEG, PNG, TIFF, and BMP. You can configure typesetting preferences to have your desired output design. It also offers numerous embedded fonts available for typesetting. With Aspose.TeX for Python, you can define your own interface for input gathering or choose to accept input from a local directory or from a ZIP archive.
Home-page: https://products.aspose.com/tex/python-net/
Author: Aspose
License: Other/Proprietary License
Project-URL: Blog, https://blog.aspose.com/categories/aspose.tex-product-family/
Project-URL: Demos, https://products.aspose.app/tex/family/
Project-URL: Docs, https://docs.aspose.com/tex/python-net/
Project-URL: Free Support, https://forum.aspose.com/c/tex/
Project-URL: API Reference, https://reference.aspose.com/tex/python-net/
Project-URL: Temporary License, https://purchase.aspose.com/temporary-license/
Keywords: Aspose.TeX Aspose.Total Conholdate.Total Conholdate Aspose TeX TeX-Engine TeX-Format LaTeX LaTeX-Python TeX-API LaTeX-API LaTeX-to-SVG LaTeX-to-PNG LaTeX-to-PDF TeX-to-PNG Pythom TeX-Extension TeX-Creator TypeSetting TypeSet Windows-Azure Conversion Component Standard XPS PDF JPEG PNG TIFF BMP Assembly Component Library Aspose.Total Conholdate Conholdate.Total
Platform: win_amd64
Classifier: Development Status :: 5 - Production/Stable
Classifier: Intended Audience :: Developers
Classifier: Intended Audience :: Education
Classifier: License :: Other/Proprietary License
Classifier: Operating System :: Microsoft :: Windows
Classifier: Operating System :: POSIX :: Linux
Classifier: Operating System :: Unix
Classifier: Programming Language :: Python :: 3 :: Only
Classifier: Programming Language :: Python :: 3.6
Classifier: Programming Language :: Python :: 3.7
Classifier: Programming Language :: Python :: 3.8
Classifier: Programming Language :: Python :: 3.9
Classifier: Programming Language :: Python :: 3.10
Classifier: Programming Language :: Python :: 3.11
Classifier: Topic :: Software Development
Classifier: Topic :: Software Development :: Libraries
Classifier: Topic :: Office/Business
Classifier: Topic :: Office/Business :: Office Suites
Requires-Python: >=3.6,<3.14
